yt_srt_gen/__init__.py
yt_srt_gen/cli.py
yt_srt_gen-0.1.5.dist-info/licenses/LICENSE
yt_srt_gen-0.1.5.dist-info/METADATA
yt_srt_gen-0.1.5.dist-info/WHEEL
yt_srt_gen-0.1.5.dist-info/entry_points.txt
yt_srt_gen-0.1.5.dist-info/top_level.txt
yt_srt_gen-0.1.5.dist-info/RECORD
