Metadata-Version: 2.4
Name: yt-srt-gen
Version: 0.1.5
Summary: Download YouTube videos, generate and translate subtitles
Author-email: Kirill Fertikov <kirill.fertikov@gmail.com>
License: GPL-3.0-or-later
Project-URL: Repository, https://github.com/fertkir/yt-srt-gen
License-File: LICENSE
Requires-Dist: yt-dlp==2026.01.31
Requires-Dist: openai-whisper==20250625
Requires-Dist: googletrans==4.0.2
Requires-Dist: tqdm==4.67.1
Dynamic: license-file
